scanner/__init__.py
scanner/metadata_pb2.py
scanner/sampler_args_pb2.py
scanner/sink_args_pb2.py
scanner/source_args_pb2.py
scanner/types_pb2.py
scanner/engine/__init__.py
scanner/engine/rpc_pb2.py
scanner/engine/rpc_pb2_grpc.py
scanner/stdlib/__init__.py
scanner/stdlib/stdlib_pb2.py
scannerpy/__init__.py
scannerpy/_python.cpython-36m-darwin.so
scannerpy/column.py
scannerpy/common.py
scannerpy/config.py
scannerpy/database.py
scannerpy/job.py
scannerpy/kernel.py
scannerpy/op.py
scannerpy/partitioner.py
scannerpy/profiler.py
scannerpy/protobuf_generator.py
scannerpy/sampler.py
scannerpy/sink.py
scannerpy/source.py
scannerpy/streams.py
scannerpy/table.py
scannerpy/cmake/Op.cmake
scannerpy/cmake/Modules/FindCaffe.cmake
scannerpy/cmake/Modules/FindEigen.cmake
scannerpy/cmake/Modules/FindFFmpeg.cmake
scannerpy/cmake/Modules/FindFolly.cmake
scannerpy/cmake/Modules/FindGFlags.cmake
scannerpy/cmake/Modules/FindGRPC.cmake
scannerpy/cmake/Modules/FindGipuma.cmake
scannerpy/cmake/Modules/FindGlog.cmake
scannerpy/cmake/Modules/FindGoogleTest.cmake
scannerpy/cmake/Modules/FindHalide.cmake
scannerpy/cmake/Modules/FindHwang.cmake
scannerpy/cmake/Modules/FindIconv.cmake
scannerpy/cmake/Modules/FindMFX.cmake
scannerpy/cmake/Modules/FindNVCUVID.cmake
scannerpy/cmake/Modules/FindOpenPose.cmake
scannerpy/cmake/Modules/FindProxygen.cmake
scannerpy/cmake/Modules/FindSaneProtobuf.cmake
scannerpy/cmake/Modules/FindStruck.cmake
scannerpy/cmake/Modules/FindTinyToml.cmake
scannerpy/include/scanner/metadata.pb.h
scannerpy/include/scanner/sampler_args.pb.h
scannerpy/include/scanner/sink_args.pb.h
scannerpy/include/scanner/source_args.pb.h
scannerpy/include/scanner/types.pb.h
scannerpy/include/scanner/api/database.h
scannerpy/include/scanner/api/enumerator.h
scannerpy/include/scanner/api/frame.h
scannerpy/include/scanner/api/kernel.h
scannerpy/include/scanner/api/op.h
scannerpy/include/scanner/api/sink.h
scannerpy-0.2.1.dist-info/METADATA
scannerpy-0.2.1.dist-info/RECORD
scannerpy-0.2.1.dist-info/WHEEL
scannerpy-0.2.1.dist-info/top_level.txt
