Metadata-Version: 2.1
Name: scannerpy
Version: 0.2.1
Summary: Efficient video analysis at scale
Home-page: https://github.com/scanner-research/scanner
Author: Alex Poms and Will Crichton
Author-email: wcrichto@cs.stanford.edu
License: Apache 2.0
Keywords: video distributed gpu
Platform: UNKNOWN
Requires-Dist: protobuf (==3.5.1)
Requires-Dist: grpcio (==1.12.0)
Requires-Dist: toml (>=0.9.2)
Requires-Dist: enum34 (>=1.1.6)
Requires-Dist: numpy (>=1.12.0)
Requires-Dist: scipy (>=0.18.1)
Requires-Dist: tqdm (>=4.19.5)
Requires-Dist: cloudpickle (>=0.5.2)
Requires-Dist: psycopg2 (==2.7.4)
Requires-Dist: testing.postgresql (==1.3.0)
